Metadata-Version: 2.1
Name: bisheng-langchain
Version: 1.3.1
Summary: bisheng langchain modules
Home-page: https://github.com/dataelement/bisheng
Author: DataElem
Author-email: contact@dataelem.com
License: Apache 2.0
Classifier: Programming Language :: Python :: 3
Classifier: Programming Language :: Python :: 3.6
Classifier: Programming Language :: Python :: 3.7
Classifier: Programming Language :: Python :: 3.8
Classifier: Programming Language :: Python :: 3.9
Classifier: License :: OSI Approved :: Apache Software License
Classifier: Operating System :: OS Independent
Requires-Python: >=3.6
Requires-Dist: langchain==0.3.*
Requires-Dist: zhipuai
Requires-Dist: websocket-client
Requires-Dist: elasticsearch
Requires-Dist: opencv-python==4.5.5.64
Requires-Dist: Pillow==9.5.0
Requires-Dist: bisheng-pyautogen
Requires-Dist: jieba==0.42.1
Requires-Dist: pydantic
Requires-Dist: pymupdf==1.26.*
Requires-Dist: shapely==2.0.2
Requires-Dist: filetype==1.2.0
Requires-Dist: langgraph==0.3.*
Requires-Dist: openai==1.*
Requires-Dist: langchain-openai==0.3.*
Requires-Dist: llama-index==0.9.48
Requires-Dist: bisheng-ragas==1.*
